{
  "AVAILABILITY_ZONES": [
    "1",
    "2",
    "3"
  ],
  "AVAILABILITY_ZONES_SECONDARY": [],
  "CONNECTIVITY_RESOURCE_GROUP": "rg-alz-connectivity",
  "CONNECTIVITY_SUBSCRIPTION_ID": "14563f67-00f5-4532-815e-c0994483f023",
  "IDENTITY_SUBSCRIPTION_ID": "accbdc8b-f02a-4cff-bcfc-660b4eb73217",
  "LOCATION": "swedencentral",
  "LOGGING_RESOURCE_GROUP": "rg-alz-logging",
  "MANAGEMENT_SUBSCRIPTION_ID": "9bbb44cb-ed3a-485b-bb89-3ac91bdf3319",
  "NETWORK_TYPE": "hubNetworking",
  "MANAGEMENT_GROUP_ID": "alz",
  "PREFIX": "alz",
  "RELEASE_VERSION": "v0.23.0",
  "ROOT_PARENT_MANAGEMENT_GROUP_ID": "e87e3c47-f133-4bb3-8d97-e5eadf26013e",
  "SECONDARYLOCATION": "",
  "SECURITY_SUBSCRIPTION_ID": "677f21ab-db02-4943-aa0a-d690b36d2b9d"
}
